[
  {
    "Ticker": "ASML",
    "Name": "ASML Holding NV",
    "Qty": 28.39,
    "Avg Buy Price (P/S)": 663.55,
    "LTP": 747.07,
    "Buy Value": 18839,
    "Present Value": 21210.06,
    "P&L (%)": 12.58684349333134,
    "Allocation (%)": 2.59,
    "Price Change (1D)": 0.07
  },
  {
    "Ticker": "AVGO",
    "Name": "Broadcom Inc",
    "Qty": 88.02,
    "Avg Buy Price (P/S)": 181.77,
    "LTP": 241.97,
    "Buy Value": 16000,
    "Present Value": 21298.19,
    "P&L (%)": 33.11877647576607,
    "Allocation (%)": 2.6,
    "Price Change (1D)": 1.06
  },
  {
    "Ticker": "HCA",
    "Name": "HCA Healthcare Inc",
    "Qty": 15.05,
    "Avg Buy Price (P/S)": 332.22,
    "LTP": 378.65,
    "Buy Value": 5000,
    "Present Value": 5698.68,
    "P&L (%)": 13.975678767082037,
    "Allocation (%)": 0.69,
    "Price Change (1D)": 0.06
  },
  {
    "Ticker": "MSFT",
    "Name": "Microsoft Corp",
    "Qty": 92.29,
    "Avg Buy Price (P/S)": 389.74,
    "LTP": 458.68,
    "Buy Value": 35970,
    "Present Value": 42331.57,
    "P&L (%)": 17.688715553959046,
    "Allocation (%)": 5.18,
    "Price Change (1D)": 0.29
  },
  {
    "Ticker": "NKE",
    "Name": "Nike Inc",
    "Qty": 185.97,
    "Avg Buy Price (P/S)": 74.82,
    "LTP": 61.44,
    "Buy Value": 13916,
    "Present Value": 11425.99,
    "P&L (%)": -17.882919005613466,
    "Allocation (%)": 1.4,
    "Price Change (1D)": -0.55
  },
  {
    "Ticker": "NVDA",
    "Name": "NVIDIA Corp",
    "Qty": 243.88,
    "Avg Buy Price (P/S)": 108.92,
    "LTP": 139.19,
    "Buy Value": 26565,
    "Present Value": 33946.18,
    "P&L (%)": 27.79103929489533,
    "Allocation (%)": 4.15,
    "Price Change (1D)": 3.25
  },
  {
    "Ticker": "PANW",
    "Name": "Palo Alto Networks Inc",
    "Qty": 141.39,
    "Avg Buy Price (P/S)": 178.04,
    "LTP": 185.82,
    "Buy Value": 25175,
    "Present Value": 26274.76,
    "P&L (%)": 4.369804538306,
    "Allocation (%)": 3.21,
    "Price Change (1D)": -1.05
  },
  {
    "Ticker": "AMD",
    "Name": "Advanced Micro Devices Inc",
    "Qty": 236.78,
    "Avg Buy Price (P/S)": 109.8,
    "LTP": 113.03,
    "Buy Value": 26000,
    "Present Value": 26764.14,
    "P&L (%)": 2.9417122040072896,
    "Allocation (%)": 3.27,
    "Price Change (1D)": 0.15
  },
  {
    "Ticker": "AMZN",
    "Name": "Amazon.com Inc",
    "Qty": 213.79,
    "Avg Buy Price (P/S)": 180.36,
    "LTP": 205.7,
    "Buy Value": 38560,
    "Present Value": 43976.6,
    "P&L (%)": 14.04967842093589,
    "Allocation (%)": 5.38,
    "Price Change (1D)": 0.48
  },
  {
    "Ticker": "NVO",
    "Name": "Novo Nordisk A/S",
    "Qty": 513.46,
    "Avg Buy Price (P/S)": 66.21,
    "LTP": 69.46,
    "Buy Value": 34000,
    "Present Value": 35665.2,
    "P&L (%)": 4.908624074913156,
    "Allocation (%)": 4.37,
    "Price Change (1D)": 1.25
  },
  {
    "Ticker": "GOOGL",
    "Name": "Alphabet Inc Class A",
    "Qty": 317.29,
    "Avg Buy Price (P/S)": 153.23,
    "LTP": 171.86,
    "Buy Value": 48620,
    "Present Value": 54529.97,
    "P&L (%)": 12.158193565228757,
    "Allocation (%)": 6.68,
    "Price Change (1D)": -0.29
  },
  {
    "Ticker": "META",
    "Name": "Meta Platforms Inc",
    "Qty": 61.91,
    "Avg Buy Price (P/S)": 516.87,
    "LTP": 645.05,
    "Buy Value": 32000,
    "Present Value": 39935.04,
    "P&L (%)": 24.799272544353503,
    "Allocation (%)": 4.89,
    "Price Change (1D)": 0.23
  },
  {
    "Ticker": "CRWD",
    "Name": "Crowdstrike Holdings Inc",
    "Qty": 18.96,
    "Avg Buy Price (P/S)": 316.45,
    "LTP": 458.81,
    "Buy Value": 6000,
    "Present Value": 8699.03,
    "P&L (%)": 44.986569758255655,
    "Allocation (%)": 1.06,
    "Price Change (1D)": -2.14
  },
  {
    "Ticker": "NFLX",
    "Name": "Netflix Inc",
    "Qty": 18.58,
    "Avg Buy Price (P/S)": 861.14,
    "LTP": 1184.86,
    "Buy Value": 16000,
    "Present Value": 22014.69,
    "P&L (%)": 37.59202917063427,
    "Allocation (%)": 2.69,
    "Price Change (1D)": -1.96
  },
  {
    "Ticker": "MELI",
    "Name": "MercadoLibre Inc",
    "Qty": 6.06,
    "Avg Buy Price (P/S)": 1978.23,
    "LTP": 2545.49,
    "Buy Value": 12000,
    "Present Value": 15440.94,
    "P&L (%)": 28.67512877673474,
    "Allocation (%)": 1.89,
    "Price Change (1D)": -0.2
  },
  {
    "Ticker": "AAPL",
    "Name": "Apple Inc",
    "Qty": 47.26,
    "Avg Buy Price (P/S)": 172.42,
    "LTP": 199.95,
    "Buy Value": 8150,
    "Present Value": 9451.02,
    "P&L (%)": 15.966825194293008,
    "Allocation (%)": 1.15,
    "Price Change (1D)": -0.23
  },
  {
    "Ticker": "LLY",
    "Name": "Eli Lilly And Co",
    "Qty": 17.18,
    "Avg Buy Price (P/S)": 756.29,
    "LTP": 722.57,
    "Buy Value": 13000,
    "Present Value": 12420.25,
    "P&L (%)": -4.458607148051661,
    "Allocation (%)": 1.52,
    "Price Change (1D)": 0.44
  },
  {
    "Ticker": "NU",
    "Name": "Nu Holdings Ltd",
    "Qty": 1167.07,
    "Avg Buy Price (P/S)": 11.99,
    "LTP": 11.99,
    "Buy Value": 14000,
    "Present Value": 13993.22,
    "P&L (%)": 0,
    "Allocation (%)": 1.71,
    "Price Change (1D)": -1.72
  },
  {
    "Ticker": "UNH",
    "Name": "UnitedHealth Group Inc",
    "Qty": 73.17,
    "Avg Buy Price (P/S)": 314.33,
    "LTP": 298.17,
    "Buy Value": 23000,
    "Present Value": 21817.39,
    "P&L (%)": -5.14109375497088,
    "Allocation (%)": 2.67,
    "Price Change (1D)": 0.02
  },
  {
    "Ticker": "TSM",
    "Name": "Taiwan Semicndctr Mnufctrng Co Ltd",
    "Qty": 36.63,
    "Avg Buy Price (P/S)": 163.79,
    "LTP": 197.15,
    "Buy Value": 6000,
    "Present Value": 7221.8,
    "P&L (%)": 20.367543806093177,
    "Allocation (%)": 0.88,
    "Price Change (1D)": 0.51
  },
  {
    "Ticker": "ADBE",
    "Name": "Adobe Inc",
    "Qty": 24.37,
    "Avg Buy Price (P/S)": 410.29,
    "LTP": 413.36,
    "Buy Value": 10000,
    "Present Value": 10074.82,
    "P&L (%)": 0.7482512369299746,
    "Allocation (%)": 1.23,
    "Price Change (1D)": 0.27
  },
  {
    "Ticker": "BOTZ",
    "Name": "Global X Robotics and Artificial Intelligence ETF",
    "Qty": 245.79,
    "Avg Buy Price (P/S)": 34.58,
    "LTP": 31.31,
    "Buy Value": 8500,
    "Present Value": 7695.68,
    "P&L (%)": -9.456333140543666,
    "Allocation (%)": 0.94,
    "Price Change (1D)": 0.74
  },
  {
    "Ticker": "QQQM",
    "Name": "Invesco NASDAQ 100 ETF",
    "Qty": 372.58,
    "Avg Buy Price (P/S)": 192.44,
    "LTP": 214.09,
    "Buy Value": 71700.55200205884,
    "Present Value": 79766.08,
    "P&L (%)": 11.250259821242988,
    "Allocation (%)": 9.77,
    "Price Change (1D)": 0.2
  },
  {
    "Ticker": "IVV",
    "Name": "iShares Core S&P 500 ETF",
    "Qty": 0,
    "Avg Buy Price (P/S)": 0,
    "LTP": 592.78,
    "Buy Value": 0,
    "Present Value": 0,
    "P&L (%)": "#DIV/0!",
    "Allocation (%)": 0,
    "Price Change (1D)": 0.4
  },
  {
    "Ticker": "XLK",
    "Name": "Technology Select Sector SPDR Fund",
    "Qty": 180.18,
    "Avg Buy Price (P/S)": 230.29,
    "LTP": 231.63,
    "Buy Value": 41495,
    "Present Value": 41735.09,
    "P&L (%)": 0.581875027139695,
    "Allocation (%)": 5.11,
    "Price Change (1D)": 0.17
  },
  {
    "Ticker": "IYW",
    "Name": "iShares US Technology ETF",
    "Qty": 147.7,
    "Avg Buy Price (P/S)": 162.09,
    "LTP": 158.67,
    "Buy Value": 23942,
    "Present Value": 23435.55,
    "P&L (%)": -2.1099389228206653,
    "Allocation (%)": 2.87,
    "Price Change (1D)": 0.27
  },
  {
    "Ticker": "SOXX",
    "Name": "iShares Semiconductor ETF",
    "Qty": 263.86,
    "Avg Buy Price (P/S)": 185.12,
    "LTP": 209.09,
    "Buy Value": 48847,
    "Present Value": 55171.81,
    "P&L (%)": 12.948357821953326,
    "Allocation (%)": 6.76,
    "Price Change (1D)": 0.41
  },
  {
    "Ticker": "FXI",
    "Name": "iShares China Large-Cap ETF",
    "Qty": 299.81,
    "Avg Buy Price (P/S)": 36.76,
    "LTP": 35.62,
    "Buy Value": 11022,
    "Present Value": 10679.23,
    "P&L (%)": -3.1011969532100125,
    "Allocation (%)": 1.3,
    "Price Change (1D)": 1.08
  },
  {
    "Ticker": "IJR",
    "Name": "iShares Core S&P Small-Cap ETF",
    "Qty": 235.43,
    "Avg Buy Price (P/S)": 101.98,
    "LTP": 105.84,
    "Buy Value": 24010,
    "Present Value": 24918.22,
    "P&L (%)": 3.785055893312413,
    "Allocation (%)": 3.05,
    "Price Change (1D)": 0.47
  },
  {
    "Ticker": "VOO",
    "Name": "Vanguard S&P 500 ETF",
    "Qty": 91.22,
    "Avg Buy Price (P/S)": 476.24,
    "LTP": 542.32,
    "Buy Value": 43447.802926793665,
    "Present Value": 49475.31,
    "P&L (%)": 13.87535696287587,
    "Allocation (%)": 6.06,
    "Price Change (1D)": 0.39
  },
  {
    "Ticker": "BTCUSD",
    "Name": "Bitcoin ",
    "Qty": 0.42,
    "Avg Buy Price (P/S)": 85329.28,
    "LTP": 105333.9,
    "Buy Value": 36056.43045554677,
    "Present Value": 44509.5,
    "P&L (%)": 23.444027653813553,
    "Allocation (%)": 5.45,
    "Price Change (1D)": -0.3
  }
]